magic_stubs/__init__.py
magic_stubs/extension.py
magic_stubs/py.typed
magic_stubs-0.2.3.dist-info/METADATA
magic_stubs-0.2.3.dist-info/WHEEL
magic_stubs-0.2.3.dist-info/top_level.txt
magic_stubs-0.2.3.dist-info/RECORD
