Metadata-Version: 2.1
Name: magic_stubs
Version: 0.2.3
Summary: Auto implement function stubs
Home-page: https://github.com/jackpeck/magic-stubs
Author: jackpeck
License: MIT
Project-URL: Bug Tracker, https://github.com/jackpeck/magic-stubs/issues
Platform: unix
Platform: linux
Platform: osx
Platform: cygwin
Platform: win32
Classifier: Programming Language :: Python :: 3
Classifier: Programming Language :: Python :: 3 :: Only
Classifier: License :: OSI Approved :: MIT License
Classifier: Operating System :: OS Independent
Requires-Dist: astor
Requires-Dist: appdirs
Requires-Dist: openai
Requires-Dist: magic-codec
